specless/__init__.py
specless/automaton/__init__.py
specless/automaton/base.py
specless/automaton/dfa.py
specless/automaton/factory.py
specless/automaton/fdfa.py
specless/automaton/mps.py
specless/automaton/pdfa.py
specless/automaton/product.py
specless/automaton/transition_system.py
specless/automaton/types.py
specless/automaton/utils.py
specless/cli/__init__.py
specless/const.py
specless/dataset.py
specless/factory/__init__.py
specless/factory/builder.py
specless/factory/object_factory.py
specless/factory/tspadapter.py
specless/inference/__init__.py
specless/inference/base.py
specless/inference/edsm.py
specless/inference/partial_order.py
specless/inference/timed_partial_order.py
specless/inference.py
specless/io.py
specless/parser.py
specless/specification/__init__.py
specless/specification/base.py
specless/specification/dfa.py
specless/specification/multispec.py
specless/specification/partial_order.py
specless/specification/pdfa.py
specless/specification/timed_partial_order.py
specless/specification.py
specless/strategy.py
specless/synthesis.py
specless/tsp/solver/__init__.py
specless/tsp/solver/base.py
specless/tsp/solver/milp.py
specless/tsp/tsp.py
specless/typing.py
specless/wrapper/__init__.py
specless/wrapper/actionwrapper.py
specless/wrapper/labelwrapper.py
specless/wrapper/minigridwrapper.py
specless/wrapper/selectstatewrapper.py
specless/wrapper/tswrapper.py
specless/wrapper/utils.py
specless-0.0.2.dist-info/LICENSE
specless-0.0.2.dist-info/METADATA
specless-0.0.2.dist-info/WHEEL
specless-0.0.2.dist-info/RECORD
