Metadata-Version: 2.1
Name: specless
Version: 0.0.2
Summary: A package to learn specification and synthesize strategy from demonstrations
License: LICENSE
Author: Kandai Watanabe
Author-email: kandai.wata@gmail.com
Requires-Python: >=3.8,<4.0
Classifier: License :: Other/Proprietary License
Classifier: Programming Language :: Python :: 3
Classifier: Programming Language :: Python :: 3.8
Classifier: Programming Language :: Python :: 3.9
Classifier: Programming Language :: Python :: 3.10
Classifier: Programming Language :: Python :: 3.11
Classifier: Programming Language :: Python :: 3.12
